synergech_doc_extractor/__init__.py
synergech_doc_extractor/base.py
synergech_doc_extractor/exception_handling.py
synergech_doc_extractor/extractor_type.py
synergech_doc_extractor/extractors.py
synergech_doc_extractor/main.py
synergech_doc_extractor/test.py
synergech_doc_extractor/utils.py
synergech_doc_extractor-0.1.4.dist-info/METADATA
synergech_doc_extractor-0.1.4.dist-info/WHEEL
synergech_doc_extractor-0.1.4.dist-info/top_level.txt
synergech_doc_extractor-0.1.4.dist-info/RECORD
